ssh_metrics/__init__.py
ssh_metrics/models.py
ssh_metrics/regexes.py
aeliant_ssh_metrics-0.1.0.dist-info/LICENSE
aeliant_ssh_metrics-0.1.0.dist-info/METADATA
aeliant_ssh_metrics-0.1.0.dist-info/WHEEL
aeliant_ssh_metrics-0.1.0.dist-info/entry_points.txt
aeliant_ssh_metrics-0.1.0.dist-info/top_level.txt
aeliant_ssh_metrics-0.1.0.dist-info/RECORD
