Metadata-Version: 2.1
Name: aeliant-ssh-metrics
Version: 0.1.0
Summary: Gather SSH metrics from syslog files
Home-page: https://github.com/aeliant/ssh-metrics
Author: Hamza ESSAYEGH
Author-email: hamza.essayegh@protonmail.com
License: MIT
Platform: UNKNOWN
Classifier: License :: OSI Approved :: MIT License
Classifier: Programming Language :: Python :: 3
Classifier: Programming Language :: Python :: 3.7
Requires-Dist: click
Requires-Dist: inflection
Requires-Dist: tabulate
